LICENSE
MANIFEST.in
README.rst
requirements.txt
setup.cfg
setup.py
deepsignal/__init__.py
deepsignal/call_modifications.py
deepsignal/deepsignal.py
deepsignal/denoise.py
deepsignal/extract_features.py
deepsignal/layers.py
deepsignal/model.py
deepsignal/train_model.py
deepsignal.egg-info/PKG-INFO
deepsignal.egg-info/SOURCES.txt
deepsignal.egg-info/dependency_links.txt
deepsignal.egg-info/entry_points.txt
deepsignal.egg-info/not-zip-safe
deepsignal.egg-info/requires.txt
deepsignal.egg-info/top_level.txt
deepsignal/utils/__init__.py
deepsignal/utils/process_utils.py
deepsignal/utils/ref_reader.py
deepsignal/utils/tf_utils.py