Metadata-Version: 1.1
Name: deepsignal
Version: 0.2.0
Summary: A deep-learning method for detecting DNA methylation state from Oxford Nanopore sequencing reads
Home-page: https://github.com/bioinfomaticsCSU/deepsignal
Author: Peng Ni, Neng Huang
Author-email: 543943952@qq.com
License: GNU General Public License v3 (GPLv3)
Download-URL: https://github.com/bioinfomaticsCSU/deepsignal/archive/v0.2.0.tar.gz
Keywords: methylation,nanopore,neural network
Platform: any
Classifier: Programming Language :: Python :: 3
Classifier: Development Status :: 4 - Beta
Classifier: Natural Language :: English
Classifier: License :: OSI Approved :: GNU General Public License v3 (GPLv3)
Classifier: Operating System :: OS Independent
